git_warlock/__init__.py
git_warlock/git-warlock.py
git_warlock/main.py
git_warlock-1.0.2.dist-info/METADATA
git_warlock-1.0.2.dist-info/WHEEL
git_warlock-1.0.2.dist-info/entry_points.txt
git_warlock-1.0.2.dist-info/top_level.txt
git_warlock-1.0.2.dist-info/RECORD
